workstation/__init__.py
workstation/cli.py
workstation/fish.py
workstation/jupyterlab.py
workstation/miscellaneous.py
workstation/nvm.py
workstation/os_manager.py
workstation/python.py
workstation/resources/.p10k.zsh
workstation/resources/.zshrc
workstation/resources/tilix.dconf
workstation/resources/zshrc/banner.zsh
workstation/resources/zshrc/init.zsh
workstation/resources/zshrc/nvm.zsh
workstation/resources/zshrc/poetry.zsh
workstation/resources/zshrc/pyenv.zsh
workstation/resources/zshrc/sdkman.zsh
workstation/resources/zshrc/virtualenv.zsh
workstation/sdkman.py
workstation/terminal.py
workstation/utils.py
workstation/zsh.py
workstation_cli-0.1.1.dist-info/entry_points.txt
workstation_cli-0.1.1.dist-info/WHEEL
workstation_cli-0.1.1.dist-info/METADATA
workstation_cli-0.1.1.dist-info/RECORD
