Metadata-Version: 2.1
Name: workstation-cli
Version: 0.1.1
Summary: Python lib for my personal workstation setup
Home-page: https://github.com/militu/workstation-cli
License: MIT
Author: Victor Mazzeo
Author-email: victor.mazzeo@groupeseloger.com
Requires-Python: >=3.8,<4.0
Classifier: License :: OSI Approved :: MIT License
Classifier: Programming Language :: Python :: 3
Classifier: Programming Language :: Python :: 3.10
Classifier: Programming Language :: Python :: 3.8
Classifier: Programming Language :: Python :: 3.9
Requires-Dist: click (>=8.0.3,<9.0.0)
Requires-Dist: distro (>=1.6.0,<2.0.0)
Requires-Dist: loguru (==0.5.3)
Requires-Dist: wget (>=3.2,<4.0)
Project-URL: Changelog, https://github.com/militu/workstation-cli/releases
Project-URL: Documentation, https://militu.github.io/workstation-cli
Project-URL: Repository, https://github.com/militu/workstation-cli
